plenoptisign/__init__.py
plenoptisign/constants.py
plenoptisign/mainclass.py
plenoptisign/plt_3d.py
plenoptisign/plt_refo.py
plenoptisign/plt_tria.py
plenoptisign/refo.py
plenoptisign/solver.py
plenoptisign/tria.py
plenoptisign/bin/__init__.py
plenoptisign/bin/cgi_script.py
plenoptisign/bin/cli_script.py
plenoptisign/gui/__init__.py
plenoptisign/gui/gui_app.py
plenoptisign/gui/widget_abt.py
plenoptisign/gui/widget_cfg.py
plenoptisign/gui/widget_cmd.py
plenoptisign/gui/widget_con.py
plenoptisign/gui/widget_men.py
plenoptisign/gui/widget_plt.py
plenoptisign/gui/cfg/__init__.py
plenoptisign/gui/cfg/cfg.py
plenoptisign/gui/misc/circlecompass_1055093.icns
plenoptisign/gui/misc/circlecompass_1055093.ico
plenoptisign-1.1.3.data/data/misc/circlecompass_1055093.ico
plenoptisign-1.1.3.data/scripts/cli_script.py
plenoptisign-1.1.3.dist-info/LICENSE.rst
plenoptisign-1.1.3.dist-info/METADATA
plenoptisign-1.1.3.dist-info/WHEEL
plenoptisign-1.1.3.dist-info/entry_points.txt
plenoptisign-1.1.3.dist-info/top_level.txt
plenoptisign-1.1.3.dist-info/RECORD
