Metadata-Version: 2.1
Name: plenoptisign
Version: 1.1.3
Summary: Light field geometry estimator for a Standard Plenoptic Camera (SPC)
Home-page: http://github.com/hahnec/plenoptisign
Author: Christopher Hahne
Author-email: inbox@christopherhahne.de
License: GNU GPL V3.0
Keywords: plenoptic camera optics design software
Platform: UNKNOWN
Requires-Dist: numpy
Requires-Dist: matplotlib
